Metadata-Version: 2.4
Name: pytelefonipapi
Version: 0.0.1
Summary: Python services for convenient work with telefon-ip.ru api
Author: kebrick
Author-email: ruban.kebr@gmail.com
License: MIT
Project-URL: Source, https://github.com/kebrick/pytelefonipapi
Project-URL: Tracker, https://github.com/kebrick/pytelefonipapi/issues
Classifier: Programming Language :: Python :: 3
Classifier: Programming Language :: Python :: 3.10
Classifier: Programming Language :: Python :: 3.11
Classifier: Programming Language :: Python :: 3.12
Classifier: Programming Language :: Python :: 3.13
Classifier: Operating System :: OS Independent
Requires-Python: >=3.10
License-File: LICENSE
Requires-Dist: requests
Requires-Dist: pydantic
Dynamic: author
Dynamic: author-email
Dynamic: classifier
Dynamic: description
Dynamic: description-content-type
Dynamic: license
Dynamic: license-file
Dynamic: project-url
Dynamic: requires-dist
Dynamic: requires-python
Dynamic: summary
